btc_address_dump/__init__.py
btc_address_dump/base58grs.py
btc_address_dump/btc_address_dump.py
btc_address_dump/coins.yaml
btc_address_dump/common_util.py
btc_address_dump/mnemonic_util.py
btc_address_dump/p2pkh_util.py
btc_address_dump/p2sh_p2wpkh_util.py
btc_address_dump/p2tr_util.py
btc_address_dump/p2wpkh_util.py
btc_address_dump/wif_util.py
btc_address_dump-0.5.0.dist-info/LICENSE
btc_address_dump-0.5.0.dist-info/METADATA
btc_address_dump-0.5.0.dist-info/WHEEL
btc_address_dump-0.5.0.dist-info/entry_points.txt
btc_address_dump-0.5.0.dist-info/top_level.txt
btc_address_dump-0.5.0.dist-info/RECORD
