Metadata-Version: 2.1
Name: btc-address-dump
Version: 0.5.0
Summary: A utility for dump btc address from mnemonic words or private key or public key
Home-page: https://github.com/10gic/btc-address-dump
Author: cig01
License: MIT License
Platform: any
Classifier: Development Status :: 4 - Beta
Classifier: Environment :: Console
Classifier: Intended Audience :: Developers
Classifier: License :: OSI Approved :: GNU Affero General Public License v3 or later (AGPLv3+)
Classifier: Operating System :: OS Independent
Classifier: Programming Language :: Python
Classifier: Programming Language :: Python :: 3.7
Classifier: Programming Language :: Python :: 3.8
Classifier: Programming Language :: Python :: 3.9
Classifier: Topic :: Software Development :: Libraries :: Python Modules
Classifier: Topic :: Text Processing
Classifier: Topic :: Utilities
Requires-Python: >=3
Requires-Dist: ecdsa (>=0.18)
Requires-Dist: base58 (>=2.0.0)
Requires-Dist: pyyaml (>=5.1)
Requires-Dist: cashaddress (>=1.0.6)
Requires-Dist: groestlcoin-hash2 (>=1.1.1)
